CHANGES.rst
COPYING.txt
MANIFEST.in
README.rst
setup.cfg
setup.py
rattail_tempmon/__init__.py
rattail_tempmon/_version.py
rattail_tempmon/client.py
rattail_tempmon/commands.py
rattail_tempmon/config.py
rattail_tempmon/emails.py
rattail_tempmon/problems.py
rattail_tempmon/server.py
rattail_tempmon/settings.py
rattail_tempmon.egg-info/PKG-INFO
rattail_tempmon.egg-info/SOURCES.txt
rattail_tempmon.egg-info/dependency_links.txt
rattail_tempmon.egg-info/entry_points.txt
rattail_tempmon.egg-info/requires.txt
rattail_tempmon.egg-info/top_level.txt
rattail_tempmon/db/__init__.py
rattail_tempmon/db/model.py
rattail_tempmon/db/alembic/README
rattail_tempmon/db/alembic/env.py
rattail_tempmon/db/alembic/script.py.mako
rattail_tempmon/db/alembic/versions/34041e1032a2_add_client_probe_notes.py
rattail_tempmon/db/alembic/versions/5f2b87474433_add_client_disk_type.py
rattail_tempmon/db/alembic/versions/75c09e11543c_grow_degrees.py
rattail_tempmon/db/alembic/versions/76d52bb064b8_add_client_delay.py
rattail_tempmon/db/alembic/versions/796084026e5b_add_appliance.py
rattail_tempmon/db/alembic/versions/7c7d205787b0_initial_tables.py
rattail_tempmon/db/alembic/versions/a2676d3dfc1e_add_appliance_images.py
rattail_tempmon/db/alembic/versions/b02c531caca5_add_more_timeouts.py
rattail_tempmon/db/alembic/versions/e9eb7fc0a451_add_client_archived.py
rattail_tempmon/db/alembic/versions/fd1df160539a_make_enabled_datetime.py
rattail_tempmon/hotcooler/__init__.py
rattail_tempmon/hotcooler/importing/__init__.py
rattail_tempmon/hotcooler/importing/tempmon.py
rattail_tempmon/templates/mail/tempmon_client_offline.html.mako
rattail_tempmon/templates/mail/tempmon_critical_high_temp.html.mako
rattail_tempmon/templates/mail/tempmon_critical_low_temp.html.mako
rattail_tempmon/templates/mail/tempmon_disabled_probes.html.mako
rattail_tempmon/templates/mail/tempmon_error.html.mako
rattail_tempmon/templates/mail/tempmon_good_temp.html.mako
rattail_tempmon/templates/mail/tempmon_high_temp.html.mako
rattail_tempmon/templates/mail/tempmon_low_temp.html.mako