Metadata-Version: 2.1
Name: rattail-tempmon
Version: 0.3.0
Summary: Retail Software Framework - Temperature monitoring add-on
Home-page: https://rattailproject.org/
Author: Lance Edgar
Author-email: lance@edbob.org
License: GNU GPL v3
Classifier: Development Status :: 3 - Alpha
Classifier: Intended Audience :: Developers
Classifier: License :: OSI Approved :: GNU General Public License v3 or later (GPLv3+)
Classifier: Natural Language :: English
Classifier: Operating System :: OS Independent
Classifier: Programming Language :: Python
Classifier: Programming Language :: Python :: 3
Classifier: Topic :: Office/Business
Classifier: Topic :: Software Development :: Libraries :: Python Modules
License-File: COPYING.txt
Requires-Dist: rattail[db]
Requires-Dist: six
Requires-Dist: sqlsoup
